app/__init__.py
app/cli.py
app/constants.py
app/main.py
app/commands/__init__.py
app/commands/cmd_generate.py
app/commands/cmd_init.py
app/commands/doc/__init__.py
app/commands/doc/cmd_create.py
app/commands/doc/cmd_delete.py
app/commands/exporter/__init__.py
app/commands/exporter/cmd_add.py
app/commands/exporter/cmd_delete.py
app/commands/repository/__init__.py
app/commands/repository/cmd_add.py
app/commands/repository/cmd_delete.py
app/commands/repository/cmd_download.py
app/commands/repository/cmd_list.py
app/services/__init__.py
app/services/init.py
app/services/doc/__init__.py
app/services/doc/create.py
app/services/doc/delete.py
app/services/exporter/__init__.py
app/services/exporter/main.py
app/services/exporter/manager.py
app/services/exporter/types/__init__.py
app/services/exporter/types/base.py
app/services/exporter/types/local.py
app/services/exporter/types/s3.py
app/services/generator/__init__.py
app/services/generator/main.py
app/services/generator/template_generation.py
app/services/generator/template_requirements.py
app/services/repository/__init__.py
app/services/repository/main.py
app/services/repository/manager.py
app/services/repository/types/__init__.py
app/services/repository/types/base.py
app/services/repository/types/s3.py
app/utils/__init__.py
app/utils/config_operations.py
app/utils/managers.py
app/utils/read_config.py
app/utils/s3.py
app/utils/segment.py
app/utils/validations.py
tests/__init__.py
tests/common.py
tests/test_doc.py
tests/test_exporter.py
tests/test_generate.py
tests/test_repository.py
docscribe-0.1.2.dist-info/LICENSE
docscribe-0.1.2.dist-info/METADATA
docscribe-0.1.2.dist-info/WHEEL
docscribe-0.1.2.dist-info/entry_points.txt
docscribe-0.1.2.dist-info/top_level.txt
docscribe-0.1.2.dist-info/RECORD
