Metadata-Version: 2.1
Name: docscribe
Version: 0.1.2
Summary: A simple tool to generate documentation, reports, and more from your codebase.
Home-page: https://github.com/sgg10/docscribe/
Author: sgg10
Author-email: sgg10.develop@gmail.com
License: MIT
Project-URL: Bug Reports, https://github.com/sgg10/docscribe/issues
Project-URL: Source, https://github.com/sgg10/docscribe/
Project-URL: Repository, https://github.com/sgg10/docscribe/
Classifier: Development Status :: 3 - Alpha
Classifier: Topic :: Utilities
Classifier: License :: OSI Approved :: MIT License
Classifier: Programming Language :: Python :: 3
Classifier: Programming Language :: Python :: 3.11
Requires-Python: >=3.11
License-File: LICENSE
Requires-Dist: click ==8.1.7
Requires-Dist: PyYAML ==6.0.1
Requires-Dist: rich ==13.7.0
Requires-Dist: boto3 ==1.34.39
Requires-Dist: docxtpl ==0.16.7
Requires-Dist: Jinja2 ==3.1.3
Requires-Dist: jsonschema ==4.21.1
Requires-Dist: packaging ==23.2
